{
  "version": "1.0.0",
  "updated": "2026-07-14T09:00:00.000Z",
  "authority": "docs/v2/FEATURE_DISCOVERY_REGISTRY.md",
  "audienceHierarchy": [
    "participant",
    "field_lead",
    "county_command",
    "regional_command",
    "state_command",
    "operator",
    "architect"
  ],
  "features": [
    {
      "id": "FEAT-LAUNCH-START",
      "title": "Steve Start / Invite Create",
      "audience": "operator",
      "journey": ["V1-JRN-INVITE-CHAIN-01"],
      "product": "Launch",
      "phase": "11.LAUNCH",
      "certification": "pending_cert",
      "nav": "/start",
      "keywords": ["invite", "steve", "bootstrap"],
      "dependsOn": [],
      "owner": "operator"
    },
    {
      "id": "FEAT-LAUNCH-ACCEPT",
      "title": "Invite Accept",
      "audience": "participant",
      "journey": ["V1-JRN-INVITE-CHAIN-01"],
      "product": "Launch",
      "phase": "11.LAUNCH",
      "certification": "pending_cert",
      "nav": "/invite/[token]",
      "keywords": ["accept", "register", "invitation"],
      "dependsOn": ["FEAT-LAUNCH-START"],
      "owner": "operator"
    },
    {
      "id": "FEAT-LAUNCH-PLACE",
      "title": "Choose / Lock Place",
      "audience": "participant",
      "journey": ["V1-JRN-INVITE-CHAIN-01", "V1-JRN-ONBOARDING-01"],
      "product": "Launch",
      "phase": "11.LAUNCH",
      "certification": "pending_cert",
      "nav": "/choose-place",
      "keywords": ["county", "school", "home"],
      "dependsOn": ["FEAT-LAUNCH-ACCEPT"],
      "owner": "operator"
    },
    {
      "id": "FEAT-NETWORK-BOARD",
      "title": "My Network Board",
      "audience": "participant",
      "journey": ["V1-JRN-INVITE-CHAIN-01", "V1-JRN-SHARE-01"],
      "product": "Network",
      "phase": "4",
      "certification": "pending_cert",
      "nav": "/network",
      "keywords": ["share", "qr", "recruit"],
      "dependsOn": ["FEAT-LAUNCH-PLACE"],
      "owner": "operator"
    },
    {
      "id": "FEAT-SHARE-SLUG",
      "title": "Personal Share Page",
      "audience": "participant",
      "journey": ["V1-JRN-SHARE-01"],
      "product": "Network",
      "phase": "4",
      "certification": "pending_cert",
      "nav": "/s/[slug]",
      "keywords": ["referral", "recruit", "slug"],
      "dependsOn": ["FEAT-NETWORK-BOARD"],
      "owner": "operator"
    },
    {
      "id": "FEAT-DIRECTORY",
      "title": "Statewide Directory Search",
      "audience": "participant",
      "journey": [],
      "product": "Discovery",
      "phase": "2",
      "certification": "implemented",
      "nav": "/directory",
      "keywords": ["search", "county", "school"],
      "dependsOn": [],
      "owner": "operator"
    },
    {
      "id": "FEAT-JULY14-AGENDA",
      "title": "July 14 Meeting Agenda",
      "audience": "participant",
      "journey": [],
      "product": "Meeting",
      "phase": "11",
      "certification": "implemented",
      "nav": "/july-14",
      "keywords": ["agenda", "meeting", "asyon"],
      "dependsOn": [],
      "owner": "state_command"
    },
    {
      "id": "FEAT-OPERATOR-COMMAND",
      "title": "Operator Command",
      "audience": "operator",
      "journey": ["V1-JRN-OPERATOR-01"],
      "product": "Operator",
      "phase": "V2-A",
      "certification": "implemented",
      "nav": "/admin?tab=command",
      "keywords": ["command", "health", "certification", "attention"],
      "dependsOn": [],
      "owner": "operator"
    },
    {
      "id": "FEAT-CERT-REGISTRY",
      "title": "Product Certification Registry",
      "audience": "architect",
      "journey": [],
      "product": "Certification",
      "phase": "v1-cert",
      "certification": "implemented",
      "nav": "docs/v1-certification/PRODUCT_CERTIFICATION_REGISTRY.md",
      "keywords": ["journey", "certified present"],
      "dependsOn": [],
      "owner": "architect"
    },
    {
      "id": "FEAT-LOCALBRAIN-API",
      "title": "LocalBrain API Surface",
      "audience": "architect",
      "journey": ["V1-JRN-LOCALBRAIN-01"],
      "product": "LIX",
      "phase": "11.7",
      "certification": "implemented",
      "nav": "/api/v1/localbrain/*",
      "keywords": ["localbrain", "living intelligence"],
      "dependsOn": [],
      "owner": "architect"
    },
    {
      "id": "FEAT-POSITION-MEMBERSHIP",
      "title": "Position Membership (Volunteer / Lead / Co-Leads)",
      "audience": "participant",
      "journey": ["V1-JRN-ONBOARDING-01"],
      "product": "Community Workspace",
      "phase": "V2-A",
      "certification": "implemented",
      "nav": "/schools/[slug] · /county/[slug]",
      "keywords": ["volunteer", "lead", "co-lead", "committee"],
      "dependsOn": [],
      "owner": "operator"
    },
    {
      "id": "FEAT-HONEST-PARTICIPATION-METRICS",
      "title": "Honest Participation Metrics",
      "audience": "participant",
      "journey": [],
      "product": "Community Workspace",
      "phase": "V2-A",
      "certification": "implemented",
      "nav": "/schools/henderson-state",
      "keywords": ["goal", "confirmed", "canonical person", "launch team"],
      "dependsOn": ["FEAT-POSITION-MEMBERSHIP"],
      "owner": "operator"
    }
  ]
}
