{
  "items": [
    {
      "id": "cnt-001",
      "public_id": "pub-cnt-001",
      "content_type": "article",
      "title": "Building a Statewide Youth Organizing Movement",
      "slug": "statewide-youth-organizing",
      "summary": "How Block Street connects counties, campuses, and volunteers across Arkansas.",
      "status": "published",
      "owner_user_id": "usr-001",
      "owner_organization_id": "org-statewide-campaign",
      "workspace_id_optional": "ws-director",
      "author_user_id": "usr-001",
      "current_version_id": "ver-001-2",
      "published_version_id": "ver-001-2",
      "audience_type": "public",
      "visibility": "public",
      "scope_type": "platform",
      "scope_id": "platform",
      "language": "en",
      "locale": "en-US",
      "authority_level": "official",
      "ai_retrieval_allowed": true,
      "channels": ["public_web", "ai_retrieval", "email"],
      "created_at": "2026-07-10T00:00:00Z",
      "updated_at": "2026-07-10T12:00:00Z",
      "published_at": "2026-07-10T12:00:00Z",
      "scheduled_at": null,
      "expires_at": null,
      "review_due_at": "2027-01-10T00:00:00Z",
      "archived_at": null,
      "taxonomy_term_ids": ["tax-topic-organizing"],
      "tag_ids": ["tag-youth", "tag-statewide"]
    },
    {
      "id": "cnt-002",
      "public_id": "pub-cnt-002",
      "content_type": "help_article",
      "title": "How to Switch Your Workspace Context",
      "slug": "help-switch-workspace",
      "summary": "Change your active organization and workspace from the Security Center.",
      "status": "published",
      "owner_user_id": "usr-001",
      "owner_organization_id": "org-statewide-campaign",
      "workspace_id_optional": null,
      "author_user_id": "usr-001",
      "current_version_id": "ver-002-1",
      "published_version_id": "ver-002-1",
      "audience_type": "authenticated",
      "visibility": "platform_internal",
      "scope_type": "platform",
      "scope_id": "platform",
      "language": "en",
      "locale": "en-US",
      "authority_level": "verified",
      "ai_retrieval_allowed": true,
      "channels": ["authenticated_web", "ai_retrieval"],
      "created_at": "2026-07-10T00:00:00Z",
      "updated_at": "2026-07-10T10:00:00Z",
      "published_at": "2026-07-10T10:00:00Z",
      "scheduled_at": null,
      "expires_at": null,
      "review_due_at": "2026-10-10T00:00:00Z",
      "archived_at": null,
      "taxonomy_term_ids": ["tax-topic-help"],
      "tag_ids": ["tag-onboarding"]
    },
    {
      "id": "cnt-003",
      "public_id": "pub-cnt-003",
      "content_type": "announcement",
      "title": "Washington County Field Team — Weekly Brief",
      "slug": "washington-county-weekly-brief",
      "summary": "Internal briefing for county organizers. Restricted to organization members.",
      "status": "published",
      "owner_user_id": "usr-002",
      "owner_organization_id": "org-washington-county",
      "workspace_id_optional": "ws-county",
      "author_user_id": "usr-002",
      "current_version_id": "ver-003-1",
      "published_version_id": "ver-003-1",
      "audience_type": "organization_members",
      "visibility": "organization_internal",
      "scope_type": "organization",
      "scope_id": "org-washington-county",
      "language": "en",
      "locale": "en-US",
      "authority_level": "editorial",
      "ai_retrieval_allowed": false,
      "channels": ["authenticated_web", "in_app_notification"],
      "created_at": "2026-07-10T00:00:00Z",
      "updated_at": "2026-07-10T11:00:00Z",
      "published_at": "2026-07-10T11:00:00Z",
      "scheduled_at": null,
      "expires_at": "2026-08-10T00:00:00Z",
      "review_due_at": null,
      "archived_at": null,
      "taxonomy_term_ids": [],
      "tag_ids": ["tag-county"]
    },
    {
      "id": "cnt-004",
      "public_id": "pub-cnt-004",
      "content_type": "article",
      "title": "Volunteer Recruitment Playbook — Draft",
      "slug": "volunteer-recruitment-playbook",
      "summary": "Draft playbook awaiting editorial review.",
      "status": "in_review",
      "owner_user_id": "usr-002",
      "owner_organization_id": "org-washington-county",
      "workspace_id_optional": "ws-county",
      "author_user_id": "usr-002",
      "current_version_id": "ver-004-1",
      "published_version_id": null,
      "audience_type": "organization_members",
      "visibility": "private_draft",
      "scope_type": "organization",
      "scope_id": "org-washington-county",
      "language": "en",
      "locale": "en-US",
      "authority_level": "draft",
      "ai_retrieval_allowed": false,
      "channels": [],
      "created_at": "2026-07-10T14:00:00Z",
      "updated_at": "2026-07-10T14:00:00Z",
      "published_at": null,
      "scheduled_at": null,
      "expires_at": null,
      "review_due_at": null,
      "archived_at": null,
      "taxonomy_term_ids": ["tax-topic-volunteers"],
      "tag_ids": []
    }
  ]
}
